{"ground":[{"pos":{"x":0,"y":-2},"texture":1},{"pos":{"x":1,"y":-2},"texture":1},{"pos":{"x":-1,"y":-2},"texture":1},{"pos":{"x":5,"y":-2},"texture":1},{"pos":{"x":21,"y":-3},"texture":1},{"pos":{"x":22,"y":-3},"texture":1},{"pos":{"x":23,"y":-3},"texture":1},{"pos":{"x":24,"y":-3},"texture":1},{"pos":{"x":-2,"y":-3},"texture":4},{"pos":{"x":-1,"y":-3},"texture":4},{"pos":{"x":0,"y":-3},"texture":4},{"pos":{"x":1,"y":-3},"texture":4},{"pos":{"x":2,"y":-3},"texture":4},{"pos":{"x":-3,"y":-3},"texture":4},{"pos":{"x":-3,"y":-2},"texture":4},{"pos":{"x":-6,"y":2},"texture":4},{"pos":{"x":-5,"y":2},"texture":4},{"pos":{"x":-4,"y":2},"texture":4},{"pos":{"x":-6,"y":1},"texture":4},{"pos":{"x":-5,"y":1},"texture":4},{"pos":{"x":-4,"y":1},"texture":4},{"pos":{"x":-6,"y":0},"texture":4},{"pos":{"x":-5,"y":0},"texture":4},{"pos":{"x":-4,"y":0},"texture":4},{"pos":{"x":-6,"y":-1},"texture":4},{"pos":{"x":-5,"y":-1},"texture":4},{"pos":{"x":-4,"y":-1},"texture":4},{"pos":{"x":-4,"y":-2},"texture":4},{"pos":{"x":-6,"y":-2},"texture":4},{"pos":{"x":-5,"y":-2},"texture":4},{"pos":{"x":-4,"y":-3},"texture":4},{"pos":{"x":-5,"y":-3},"texture":4},{"pos":{"x":-6,"y":-3},"texture":4},{"pos":{"x":3,"y":3},"texture":4},{"pos":{"x":3,"y":-2},"texture":4},{"pos":{"x":3,"y":-3},"texture":4},{"pos":{"x":4,"y":-3},"texture":4},{"pos":{"x":5,"y":-3},"texture":4},{"pos":{"x":19,"y":-2},"texture":4},{"pos":{"x":19,"y":-3},"texture":4},{"pos":{"x":38,"y":-1},"texture":4},{"pos":{"x":38,"y":-2},"texture":4},{"pos":{"x":38,"y":-3},"texture":4},{"pos":{"x":42,"y":3},"texture":4},{"pos":{"x":42,"y":2},"texture":4},{"pos":{"x":42,"y":1},"texture":4},{"pos":{"x":42,"y":0},"texture":4},{"pos":{"x":42,"y":-1},"texture":4},{"pos":{"x":42,"y":-2},"texture":4},{"pos":{"x":42,"y":-3},"texture":4},{"pos":{"x":39,"y":-3},"texture":4},{"pos":{"x":40,"y":-3},"texture":4},{"pos":{"x":41,"y":-3},"texture":4},{"pos":{"x":41,"y":-2},"texture":4},{"pos":{"x":40,"y":-2},"texture":4},{"pos":{"x":39,"y":-2},"texture":4},{"pos":{"x":39,"y":-1},"texture":4},{"pos":{"x":40,"y":-1},"texture":4},{"pos":{"x":41,"y":-1},"texture":4},{"pos":{"x":40,"y":3},"texture":4},{"pos":{"x":41,"y":3},"texture":4},{"pos":{"x":41,"y":2},"texture":4},{"pos":{"x":40,"y":2},"texture":4},{"pos":{"x":40,"y":1},"texture":4},{"pos":{"x":41,"y":1},"texture":4},{"pos":{"x":41,"y":0},"texture":4},{"pos":{"x":40,"y":0},"texture":4},{"pos":{"x":39,"y":0},"texture":4},{"pos":{"x":6,"y":-3},"texture":5},{"pos":{"x":2,"y":-2},"texture":7},{"pos":{"x":38,"y":0},"texture":7},{"pos":{"x":38,"y":3},"texture":8},{"pos":{"x":37,"y":3},"texture":8},{"pos":{"x":36,"y":3},"texture":8},{"pos":{"x":35,"y":3},"texture":8},{"pos":{"x":34,"y":3},"texture":8},{"pos":{"x":33,"y":3},"texture":8},{"pos":{"x":32,"y":3},"texture":8},{"pos":{"x":31,"y":3},"texture":8},{"pos":{"x":30,"y":3},"texture":8},{"pos":{"x":29,"y":3},"texture":8},{"pos":{"x":28,"y":3},"texture":8},{"pos":{"x":27,"y":3},"texture":8},{"pos":{"x":26,"y":3},"texture":8},{"pos":{"x":25,"y":3},"texture":8},{"pos":{"x":24,"y":3},"texture":8},{"pos":{"x":23,"y":3},"texture":8},{"pos":{"x":22,"y":3},"texture":8},{"pos":{"x":21,"y":3},"texture":8},{"pos":{"x":20,"y":3},"texture":8},{"pos":{"x":19,"y":3},"texture":8},{"pos":{"x":18,"y":3},"texture":8},{"pos":{"x":17,"y":3},"texture":8},{"pos":{"x":16,"y":3},"texture":8},{"pos":{"x":15,"y":3},"texture":8},{"pos":{"x":14,"y":3},"texture":8},{"pos":{"x":13,"y":3},"texture":8},{"pos":{"x":12,"y":3},"texture":8},{"pos":{"x":11,"y":3},"texture":8},{"pos":{"x":10,"y":3},"texture":8},{"pos":{"x":9,"y":3},"texture":8},{"pos":{"x":8,"y":3},"texture":8},{"pos":{"x":7,"y":3},"texture":8},{"pos":{"x":6,"y":3},"texture":8},{"pos":{"x":5,"y":3},"texture":8},{"pos":{"x":4,"y":3},"texture":8},{"pos":{"x":3,"y":2},"texture":8},{"pos":{"x":2,"y":3},"texture":8},{"pos":{"x":1,"y":3},"texture":8},{"pos":{"x":0,"y":3},"texture":8},{"pos":{"x":-1,"y":3},"texture":8},{"pos":{"x":-2,"y":-2},"texture":9},{"pos":{"x":-3,"y":-1},"texture":9},{"pos":{"x":4,"y":-2},"texture":9},{"pos":{"x":19,"y":-1},"texture":9},{"pos":{"x":20,"y":-3},"texture":9},{"pos":{"x":-2,"y":-1},"texture":2},{"pos":{"x":2,"y":-1}},{"pos":{"x":-2,"y":3},"texture":8},{"pos":{"x":-3,"y":3},"texture":5},{"pos":{"x":-3,"y":3},"texture":8},{"pos":{"x":-4,"y":3},"texture":4},{"pos":{"x":-5,"y":3},"texture":4},{"pos":{"x":-6,"y":3},"texture":4},{"pos":{"x":3,"y":-1},"texture":1},{"pos":{"x":4,"y":-1},"texture":2},{"pos":{"x":6,"y":-2},"texture":2},{"pos":{"x":19,"y":0},"texture":2},{"pos":{"x":26,"y":0},"texture":15},{"pos":{"x":26,"y":1},"texture":2},{"pos":{"x":25,"y":-3},"texture":1},{"pos":{"x":25,"y":-3},"texture":3},{"pos":{"x":38,"y":1}},{"pos":{"x":39,"y":2},"texture":3},{"pos":{"x":39,"y":3},"texture":3},{"pos":{"x":39,"y":3},"texture":8},{"pos":{"x":39,"y":1},"texture":7},{"pos":{"x":29,"y":1},"texture":13},{"pos":{"x":16,"y":0},"texture":13},{"pos":{"x":14,"y":-1},"texture":13},{"pos":{"x":12,"y":-1},"texture":13},{"pos":{"x":35,"y":0},"texture":13},{"pos":{"x":8,"y":-3},"texture":3},{"pos":{"x":8,"y":-2},"texture":3},{"pos":{"x":8,"y":-1},"texture":3},{"pos":{"x":8,"y":0},"texture":3},{"pos":{"x":8,"y":1}},{"pos":{"x":9,"y":1},"texture":2},{"pos":{"x":9,"y":0},"texture":5},{"pos":{"x":9,"y":-1},"texture":5},{"pos":{"x":9,"y":-2},"texture":5},{"pos":{"x":9,"y":-3},"texture":5},{"pos":{"x":18,"y":1}},{"pos":{"x":18,"y":0},"texture":3},{"pos":{"x":18,"y":-1},"texture":3},{"pos":{"x":18,"y":-2},"texture":3},{"pos":{"x":18,"y":-3},"texture":3},{"pos":{"x":20,"y":-1},"texture":2},{"pos":{"x":20,"y":-2},"texture":5},{"pos":{"x":25,"y":-2},"texture":3},{"pos":{"x":25,"y":-1},"texture":3},{"pos":{"x":25,"y":0},"texture":3},{"pos":{"x":25,"y":1}},{"pos":{"x":31,"y":0}},{"pos":{"x":31,"y":-1},"texture":3},{"pos":{"x":31,"y":-2},"texture":3},{"pos":{"x":31,"y":-3},"texture":3},{"pos":{"x":32,"y":0},"texture":2},{"pos":{"x":32,"y":-1},"texture":5},{"pos":{"x":32,"y":-2},"texture":5},{"pos":{"x":32,"y":-3},"texture":5},{"pos":{"x":-3,"y":2},"texture":5},{"pos":{"x":-3,"y":1},"texture":5},{"pos":{"x":-3,"y":0},"texture":5},{"pos":{"x":37,"y":0}},{"pos":{"x":37,"y":-1},"texture":3},{"pos":{"x":37,"y":-2},"texture":3},{"pos":{"x":37,"y":-3},"texture":3}]}